refractml/__init__.py
refractml/api.py
refractml/constants.py
refractml/decorators.py
refractml/exceptions.py
refractml/session.py
refractml/spark_distributed_session.py
refractml/utils.py
refractml/validators.py
refractml/schema/__init__.py
refractml/schema/base_schema_generator.py
refractml/schema/numpy_schema_generator.py
refractml/schema/pandas_schema_generator.py
refractml/widgets/__init__.py
refractml/widgets/fields.py
refractml/widgets/register_model.py
refractml/widgets/registered_output.py
tests/__init__.py
tests/conftest.py
tests/test_pyspark.py
tests/test_register_model.py
tests/test_schema.py
tests/test_spark_distributed_session.py
refractml-1.0.8.dist-info/METADATA
refractml-1.0.8.dist-info/WHEEL
refractml-1.0.8.dist-info/top_level.txt
refractml-1.0.8.dist-info/RECORD
